{"m_player":{"m_rows":3,"m_columns":5,"m_hotbarCount":5,"m_backpack":[{"m_id":-1,"m_quantity":0},{"m_id":-1,"m_quantity":0},{"m_id":-1,"m_quantity":0},{"m_id":-1,"m_quantity":0},{"m_id":-1,"m_quantity":0},{"m_id":-1,"m_quantity":0},{"m_id":-1,"m_quantity":0},{"m_id":-1,"m_quantity":0},{"m_id":-1,"m_quantity":0},{"m_id":5,"m_quantity":16},{"m_id":4,"m_quantity":16},{"m_id":3,"m_quantity":16},{"m_id":2,"m_quantity":16},{"m_id":-1,"m_quantity":0},{"m_id":0,"m_quantity":25}],"m_hotbar":[{"m_id":7,"m_quantity":99},{"m_id":1,"m_quantity":12},{"m_id":6,"m_quantity":1},{"m_id":-1,"m_quantity":0},{"m_id":-1,"m_quantity":0}]},"m_scenes":[{"m_id":0,"m_objectCount":0,"m_objects":[]},{"m_id":1,"m_objectCount":3,"m_objects":[{"m_itemID":1,"m_age":-1.0,"m_nextHarvest":-1,"m_water":1.0,"cx":0.0,"cy":0.0,"cz":0.0,"x":37.0,"y":4.193575859069824,"z":-3.0,"rx":0.0,"ry":0.0,"rz":0.0},{"m_itemID":1,"m_age":0.0,"m_nextHarvest":-1,"m_water":1.0,"cx":0.0,"cy":0.0,"cz":0.0,"x":38.0,"y":4.193575859069824,"z":-2.0,"rx":0.0,"ry":0.0,"rz":0.0},{"m_itemID":1,"m_age":-1.0,"m_nextHarvest":-1,"m_water":1.0,"cx":0.0,"cy":0.0,"cz":0.0,"x":39.0,"y":4.193575859069824,"z":-2.0,"rx":0.0,"ry":0.0,"rz":0.0}]}],"m_quests":[{"m_dueDay":5,"m_itemId":2,"m_itemAmount":10},{"m_dueDay":7,"m_itemId":1,"m_itemAmount":10},{"m_dueDay":5,"m_itemId":2,"m_itemAmount":11}],"m_npcs":[{"m_id":0,"m_scene":1,"m_prefab":"Hat","x":32.65875244140625,"y":5.556421756744385,"z":-11.53625202178955,"rx":0.0,"ry":170.0000762939453,"rz":0.0,"m_extraData":"0"},{"m_id":1,"m_scene":1,"m_prefab":"Questboard","x":30.663000106811525,"y":4.193575859069824,"z":-7.75,"rx":0.0,"ry":90.0,"rz":0.0,"m_extraData":"0"},{"m_id":0,"m_scene":1,"m_prefab":"Hat","x":32.65875244140625,"y":5.556421756744385,"z":-11.53625202178955,"rx":0.0,"ry":170.0000762939453,"rz":0.0,"m_extraData":"0"},{"m_id":1,"m_scene":1,"m_prefab":"Questboard","x":30.663000106811525,"y":4.193575859069824,"z":-7.75,"rx":0.0,"ry":90.0,"rz":0.0,"m_extraData":"0"},{"m_id":0,"m_scene":1,"m_prefab":"Hat","x":32.65875244140625,"y":5.556421756744385,"z":-11.53625202178955,"rx":0.0,"ry":170.0000762939453,"rz":0.0,"m_extraData":"0"},{"m_id":1,"m_scene":1,"m_prefab":"Questboard","x":30.663000106811525,"y":4.193575859069824,"z":-7.75,"rx":0.0,"ry":90.0,"rz":0.0,"m_extraData":"0"},{"m_id":0,"m_scene":1,"m_prefab":"Hat","x":32.65875244140625,"y":5.556421756744385,"z":-11.53625202178955,"rx":0.0,"ry":170.0000762939453,"rz":0.0,"m_extraData":"0"},{"m_id":1,"m_scene":1,"m_prefab":"Questboard","x":30.663000106811525,"y":4.193575859069824,"z":-7.75,"rx":0.0,"ry":90.0,"rz":0.0,"m_extraData":"0"},{"m_id":0,"m_scene":1,"m_prefab":"Hat","x":32.65875244140625,"y":5.556421756744385,"z":-11.53625202178955,"rx":0.0,"ry":170.0000762939453,"rz":0.0,"m_extraData":"0"},{"m_id":1,"m_scene":1,"m_prefab":"Questboard","x":30.663000106811525,"y":4.193575859069824,"z":-7.75,"rx":0.0,"ry":90.0,"rz":0.0,"m_extraData":"0"},{"m_id":0,"m_scene":1,"m_prefab":"Hat","x":32.65875244140625,"y":5.556421756744385,"z":-11.53625202178955,"rx":0.0,"ry":170.0000762939453,"rz":0.0,"m_extraData":"0"},{"m_id":1,"m_scene":1,"m_prefab":"Questboard","x":30.663000106811525,"y":4.193575859069824,"z":-7.75,"rx":0.0,"ry":90.0,"rz":0.0,"m_extraData":"0"},{"m_id":0,"m_scene":1,"m_prefab":"Hat","x":32.65875244140625,"y":5.556421756744385,"z":-11.53625202178955,"rx":0.0,"ry":170.0000762939453,"rz":0.0,"m_extraData":"0"},{"m_id":1,"m_scene":1,"m_prefab":"Questboard","x":30.663000106811525,"y":4.193575859069824,"z":-7.75,"rx":0.0,"ry":90.0,"rz":0.0,"m_extraData":"0"},{"m_id":0,"m_scene":1,"m_prefab":"Hat","x":32.65875244140625,"y":5.556421756744385,"z":-11.53625202178955,"rx":0.0,"ry":170.0000762939453,"rz":0.0,"m_extraData":"0"},{"m_id":1,"m_scene":1,"m_prefab":"Questboard","x":30.663000106811525,"y":4.193575859069824,"z":-7.75,"rx":0.0,"ry":90.0,"rz":0.0,"m_extraData":"0"},{"m_id":0,"m_scene":1,"m_prefab":"Hat","x":32.65875244140625,"y":5.556421756744385,"z":-11.53625202178955,"rx":0.0,"ry":170.0000762939453,"rz":0.0,"m_extraData":"0"},{"m_id":1,"m_scene":1,"m_prefab":"Questboard","x":30.663000106811525,"y":4.193575859069824,"z":-7.75,"rx":0.0,"ry":90.0,"rz":0.0,"m_extraData":"0"},{"m_id":0,"m_scene":1,"m_prefab":"Hat","x":32.65875244140625,"y":5.556421756744385,"z":-11.53625202178955,"rx":0.0,"ry":170.0000762939453,"rz":0.0,"m_extraData":"0"},{"m_id":1,"m_scene":1,"m_prefab":"Questboard","x":30.663000106811525,"y":4.193575859069824,"z":-7.75,"rx":0.0,"ry":90.0,"rz":0.0,"m_extraData":"0"},{"m_id":0,"m_scene":1,"m_prefab":"Perry_NoAnim","x":31.405000686645509,"y":5.195000171661377,"z":-12.789999961853028,"rx":0.0,"ry":315.0000915527344,"rz":0.0,"m_extraData":"0"},{"m_id":1,"m_scene":1,"m_prefab":"Questboard","x":30.663000106811525,"y":4.193575859069824,"z":-7.75,"rx":0.0,"ry":90.0,"rz":0.0,"m_extraData":"17.75285"},{"m_id":0,"m_scene":1,"m_prefab":"Hat (1)","x":32.65875244140625,"y":5.556421756744385,"z":-11.53625202178955,"rx":0.0,"ry":315.0000915527344,"rz":0.0,"m_extraData":"0"},{"m_id":1,"m_scene":1,"m_prefab":"Questboard","x":30.663000106811525,"y":4.193575859069824,"z":-7.75,"rx":0.0,"ry":90.0,"rz":0.0,"m_extraData":"0"},{"m_id":0,"m_scene":1,"m_prefab":"Hat (2)","x":32.65875244140625,"y":5.556421756744385,"z":-11.53625202178955,"rx":0.0,"ry":315.0000915527344,"rz":0.0,"m_extraData":"0"},{"m_id":1,"m_scene":1,"m_prefab":"Questboard","x":30.663000106811525,"y":4.193575859069824,"z":-7.75,"rx":0.0,"ry":90.0,"rz":0.0,"m_extraData":"0"},{"m_id":0,"m_scene":1,"m_prefab":"Hat (2)","x":32.65875244140625,"y":5.556421756744385,"z":-11.53625202178955,"rx":0.0,"ry":315.0000915527344,"rz":0.0,"m_extraData":"0"},{"m_id":1,"m_scene":1,"m_prefab":"Questboard","x":30.663000106811525,"y":4.193575859069824,"z":-7.75,"rx":0.0,"ry":90.0,"rz":0.0,"m_extraData":"0"},{"m_id":0,"m_scene":1,"m_prefab":"Perry_NoAnim","x":31.405000686645509,"y":5.195000171661377,"z":-12.789999961853028,"rx":0.0,"ry":315.0000915527344,"rz":0.0,"m_extraData":"0"},{"m_id":1,"m_scene":1,"m_prefab":"Questboard","x":30.663000106811525,"y":4.193575859069824,"z":-7.75,"rx":0.0,"ry":90.0,"rz":0.0,"m_extraData":"0"},{"m_id":0,"m_scene":1,"m_prefab":"Hat (2)","x":32.65875244140625,"y":5.556421756744385,"z":-11.53625202178955,"rx":0.0,"ry":315.0000915527344,"rz":0.0,"m_extraData":"17.78547"},{"m_id":1,"m_scene":1,"m_prefab":"Questboard","x":30.663000106811525,"y":4.193575859069824,"z":-7.75,"rx":0.0,"ry":90.0,"rz":0.0,"m_extraData":"17.94535"}],"m_day":0,"m_hour":14.420552253723145}